voice_puppet/__init__.py
voice_puppet-0.2.1.dist-info/METADATA
voice_puppet-0.2.1.dist-info/WHEEL
voice_puppet-0.2.1.dist-info/entry_points.txt
voice_puppet-0.2.1.dist-info/RECORD
