Metadata-Version: 2.3
Name: voice-puppet
Version: 0.2.1
Summary: Experimentation with voice cloning for performance.
Author-email: Sam Lavigne <splavigne@gmail.com>
Requires-Python: >=3.8
Requires-Dist: coqui-tts>=0.24.2
